neoteroi/auth/__about__.py
neoteroi/auth/__init__.py
neoteroi/auth/abc.py
neoteroi/auth/authentication.py
neoteroi/auth/authorization.py
neoteroi/auth/common.py
neoteroi/auth/errors.py
neoteroi/auth/utils.py
neoteroi/auth/jwks/__init__.py
neoteroi/auth/jwks/caching.py
neoteroi/auth/jwks/openid.py
neoteroi/auth/jwks/urls.py
neoteroi/auth/jwts/__init__.py
neoteroi_auth-0.0.3.dist-info/METADATA
neoteroi_auth-0.0.3.dist-info/WHEEL
neoteroi_auth-0.0.3.dist-info/licenses/LICENSE
neoteroi_auth-0.0.3.dist-info/RECORD
