Metadata-Version: 2.1
Name: neoteroi-auth
Version: 0.0.3
Summary: Framework to handle authentication and authorization.
Project-URL: Homepage, https://github.com/Neoteroi/auth
Project-URL: Bug Tracker, https://github.com/Neoteroi/auth/issues
Author-email: Roberto Prevato <roberto.prevato@gmail.com>
License-File: LICENSE
Keywords: authentication,authorization,claims,identity,strategy
Classifier: Development Status :: 3 - Alpha
Classifier: License :: OSI Approved :: MIT License
Classifier: Operating System :: OS Independent
Classifier: Programming Language :: Python :: 3
Classifier: Programming Language :: Python :: 3.7
Classifier: Programming Language :: Python :: 3.8
Classifier: Programming Language :: Python :: 3.9
Classifier: Programming Language :: Python :: 3.10
Classifier: Programming Language :: Python :: 3.11
Requires-Python: >=3.7
Requires-Dist: neoteroi-di<=2.0.0
Requires-Dist: typing-extensions; python_version < '3.8'
Provides-Extra: jwt
Requires-Dist: cryptography; extra == 'jwt'
Requires-Dist: pyjwt; extra == 'jwt'
